odoo/addons/project_task_internal_user/__init__.py
odoo/addons/project_task_internal_user/__manifest__.py
odoo/addons/project_task_internal_user/models/__init__.py
odoo/addons/project_task_internal_user/models/project.py
odoo12_addon_project_task_internal_user-12.0.1.0.0.dist-info/METADATA
odoo12_addon_project_task_internal_user-12.0.1.0.0.dist-info/WHEEL
odoo12_addon_project_task_internal_user-12.0.1.0.0.dist-info/top_level.txt
odoo12_addon_project_task_internal_user-12.0.1.0.0.dist-info/RECORD
